ndmanager/__init__.py
ndmanager/data.py
ndmanager/env.py
ndmanager/format.py
ndmanager/API/__init__.py
ndmanager/API/endf6.py
ndmanager/API/merge.py
ndmanager/API/nuclide.py
ndmanager/API/sha1.py
ndmanager/API/utils.py
ndmanager/API/iaea/__init__.py
ndmanager/API/iaea/iaea.py
ndmanager/API/iaea/library.py
ndmanager/API/iaea/sublibrary.py
ndmanager/API/process/__init__.py
ndmanager/API/process/base_manager.py
ndmanager/API/process/hdf5_neutron.py
ndmanager/API/process/hdf5_photon.py
ndmanager/API/process/hdf5_sublibrary.py
ndmanager/API/process/hdf5_tsl.py
ndmanager/API/process/input_parser.py
ndmanager/API/process/ndm_library.py
ndmanager/API/process/neutron_manager.py
ndmanager/API/process/photon_manager.py
ndmanager/API/process/tsl_manager.py
ndmanager/API/sampling/__init__.py
ndmanager/API/sampling/covmatrix.py
ndmanager/API/sampling/hdf5_sampling.py
ndmanager/API/sampling/pendf_sampling.py
ndmanager/API/sampling/sampling.py
ndmanager/CLI/__init__.py
ndmanager/CLI/parser.py
ndmanager/CLI/chainer/__init__.py
ndmanager/CLI/chainer/branching_ratios.py
ndmanager/CLI/chainer/build.py
ndmanager/CLI/chainer/install.py
ndmanager/CLI/chainer/listchains.py
ndmanager/CLI/chainer/main.py
ndmanager/CLI/chainer/remove.py
ndmanager/CLI/fetcher/__init__.py
ndmanager/CLI/fetcher/install.py
ndmanager/CLI/fetcher/listlibs.py
ndmanager/CLI/fetcher/main.py
ndmanager/CLI/fetcher/remove.py
ndmanager/CLI/omcer/__init__.py
ndmanager/CLI/omcer/build.py
ndmanager/CLI/omcer/clone.py
ndmanager/CLI/omcer/edit.py
ndmanager/CLI/omcer/install.py
ndmanager/CLI/omcer/listlibs.py
ndmanager/CLI/omcer/main.py
ndmanager/CLI/omcer/remove.py
ndmanager/CLI/sampler/__init__.py
ndmanager/CLI/sampler/cov.py
ndmanager/CLI/sampler/hdf5.py
ndmanager/CLI/sampler/listsamples.py
ndmanager/CLI/sampler/main.py
ndmanager/CLI/sampler/pendf.py
ndmanager/CLI/sampler/remove.py
ndmanager/_vendor/__init__.py
ndmanager/_vendor/omc_data/__init__.py
ndmanager/_vendor/omc_data/_xml.py
ndmanager/_vendor/omc_data/ace.py
ndmanager-0.6.1.dist-info/licenses/LICENSE
ndmanager-0.6.1.dist-info/METADATA
ndmanager-0.6.1.dist-info/WHEEL
ndmanager-0.6.1.dist-info/entry_points.txt
ndmanager-0.6.1.dist-info/top_level.txt
ndmanager-0.6.1.dist-info/RECORD
