Metadata-Version: 2.4
Name: ndmanager
Version: 0.6.1
Summary: Managing you nuclear data collection
Author-email: Nicolas Linden <nicolas@nlinden.com>
Project-URL: Homepage, https://github.com/nplinden/ndmanager
Classifier: Programming Language :: Python :: 3.11
Requires-Python: >=3.11
License-File: LICENSE
Requires-Dist: beautifulsoup4>=4.13.4
Requires-Dist: endf>=0.1.4
Requires-Dist: h5py>=3.14.0
Requires-Dist: lxml>=6.0.0
Requires-Dist: matplotlib>=3.10.3
Requires-Dist: numpy<2.3
Requires-Dist: pandas>=2.3.0
Requires-Dist: pyyaml>=6.0.2
Requires-Dist: requests>=2.32.4
Requires-Dist: sandy>=1.1.0
Requires-Dist: tabulate>=0.9.0
Requires-Dist: tqdm>=4.67.1
Provides-Extra: docs
Requires-Dist: sphinx>=8.2.3; extra == "docs"
Requires-Dist: sphinx-autodoc-typehints>=3.2.0; extra == "docs"
Requires-Dist: sphinx-copybutton>=0.5.2; extra == "docs"
Requires-Dist: sphinx-design>=0.6.1; extra == "docs"
Requires-Dist: pydata-sphinx-theme>=0.16.1; extra == "docs"
Dynamic: license-file
